pyrepositoryminer/__init__.py
pyrepositoryminer/__main__.py
pyrepositoryminer/analyze.py
pyrepositoryminer/commands/__init__.py
pyrepositoryminer/commands/analyze.py
pyrepositoryminer/commands/branch.py
pyrepositoryminer/commands/clone.py
pyrepositoryminer/commands/commits.py
pyrepositoryminer/commands/utils/__init__.py
pyrepositoryminer/commands/utils/commits.py
pyrepositoryminer/commands/utils/metric.py
pyrepositoryminer/metrics/__init__.py
pyrepositoryminer/metrics/diffblob/__init__.py
pyrepositoryminer/metrics/diffblob/diffpylinecount.py
pyrepositoryminer/metrics/diffblob/main.py
pyrepositoryminer/metrics/diffdir/__init__.py
pyrepositoryminer/metrics/diffdir/difftokei.py
pyrepositoryminer/metrics/diffdir/main.py
pyrepositoryminer/metrics/dir/__init__.py
pyrepositoryminer/metrics/dir/main.py
pyrepositoryminer/metrics/dir/tokei.py
pyrepositoryminer/metrics/main.py
pyrepositoryminer/metrics/nativeblob/__init__.py
pyrepositoryminer/metrics/nativeblob/complexity.py
pyrepositoryminer/metrics/nativeblob/halstead.py
pyrepositoryminer/metrics/nativeblob/linecount.py
pyrepositoryminer/metrics/nativeblob/linelength.py
pyrepositoryminer/metrics/nativeblob/main.py
pyrepositoryminer/metrics/nativeblob/maintainability.py
pyrepositoryminer/metrics/nativeblob/nesting.py
pyrepositoryminer/metrics/nativeblob/pylinecount.py
pyrepositoryminer/metrics/nativeblob/raw.py
pyrepositoryminer/metrics/nativetree/__init__.py
pyrepositoryminer/metrics/nativetree/blobcount.py
pyrepositoryminer/metrics/nativetree/cacherate.py
pyrepositoryminer/metrics/nativetree/loc.py
pyrepositoryminer/metrics/nativetree/main.py
pyrepositoryminer/metrics/nativetree/touchedlines.py
pyrepositoryminer/metrics/structs.py
pyrepositoryminer/metrics/utils.py
pyrepositoryminer/output.py
pyrepositoryminer/pobjects.py
pyrepositoryminer-0.9.1.dist-info/entry_points.txt
pyrepositoryminer-0.9.1.dist-info/LICENSE
pyrepositoryminer-0.9.1.dist-info/WHEEL
pyrepositoryminer-0.9.1.dist-info/METADATA
pyrepositoryminer-0.9.1.dist-info/RECORD
