Metadata-Version: 2.1
Name: pyrepositoryminer
Version: 0.9.1
Summary: Efficient Repository Mining in Python
Home-page: https://github.com/fabianhe/pyrepositoryminer
License: GPL-3.0-or-later
Author: Fabian Heseding
Author-email: 39628987+fabianhe@users.noreply.github.com
Requires-Python: >=3.9,<4.0
Classifier: License :: OSI Approved :: GNU General Public License v3 or later (GPLv3+)
Classifier: Programming Language :: Python :: 3
Classifier: Programming Language :: Python :: 3.10
Classifier: Programming Language :: Python :: 3.9
Requires-Dist: pygit2 (>=1.5.0,<2.0.0)
Requires-Dist: radon (>=4.5.0,<5.0.0)
Requires-Dist: typer[all] (>=0.3.2,<0.4.0)
Requires-Dist: uvloop (>=0.15.2,<0.16.0)
Project-URL: Documentation, https://github.com/fabianhe/pyrepositoryminer/blob/master/DOCS.md
Project-URL: Repository, https://github.com/fabianhe/pyrepositoryminer
